chain_breaking_polymer_networks/__init__.py
chain_breaking_polymer_networks/__main__.py
chain_breaking_polymer_networks/network.py
chain_breaking_polymer_networks/plotting.py
chain_breaking_polymer_networks/relaxation_function.py
chain_breaking_polymer_networks/single_chain.py
chain_breaking_polymer_networks-1.0.1.dist-info/METADATA
chain_breaking_polymer_networks-1.0.1.dist-info/WHEEL
chain_breaking_polymer_networks-1.0.1.dist-info/top_level.txt
chain_breaking_polymer_networks-1.0.1.dist-info/RECORD
