Metadata-Version: 2.1
Name: chain-breaking-polymer-networks
Version: 1.0.1
Summary: Chain breaking in the statistical mechanical constitutive theory of polymer networks
Home-page: https://github.com/mbuche/chain_breaking_polymer_networks
Author: Michael R. Buche
Author-email: mrb289@cornell.edu
License: MIT
Platform: UNKNOWN
Classifier: License :: OSI Approved :: MIT License
Classifier: Programming Language :: Python :: 3
Classifier: Programming Language :: Python :: 3.7
Requires-Dist: numpy
Requires-Dist: scipy
Requires-Dist: matplotlib
